upstoxalgo/__init__.py
upstoxalgo/imports_and_instrument_token.py
upstoxalgo/upstox.py
upstoxalgo/upstox_auto_auth_code.py
upstoxalgo/upstox_login_flow.py
upstoxalgo/utils.py
upstoxalgo-0.4.2.dist-info/METADATA
upstoxalgo-0.4.2.dist-info/WHEEL
upstoxalgo-0.4.2.dist-info/top_level.txt
upstoxalgo-0.4.2.dist-info/RECORD
